numgrid-2.1.2.dist-info/METADATA
numgrid-2.1.2.dist-info/WHEEL
numgrid/__init__.py
numgrid/numgrid.cp311-win_amd64.pyd
numgrid-2.1.2.dist-info/RECORD
