Metadata-Version: 2.4
Name: numgrid
Version: 2.1.2
Summary: Numerical integration grid for molecules.
Home-Page: https://github.com/dftlibs/numgrid/
Author: Radovan Bast <bast@users.noreply.github.com>
Author-email: Radovan Bast <bast@users.noreply.github.com>
License: MPL-2.0
